msg.py
agmsg/__init__.py
agmsg-1.0.5.dist-info/DESCRIPTION.rst
agmsg-1.0.5.dist-info/METADATA
agmsg-1.0.5.dist-info/RECORD
agmsg-1.0.5.dist-info/WHEEL
agmsg-1.0.5.dist-info/metadata.json
agmsg-1.0.5.dist-info/top_level.txt
msg/__init__.py
